clado_observe/__init__.py
clado_observe/agents/__init__.py
clado_observe/agents/browser_use/__init__.py
clado_observe/agents/browser_use/agent.py
clado_observe/cdp/observer.py
clado_observe/cdp/utils/base_client.py
clado_observe/cdp/utils/dom.py
clado_observe/cdp/utils/network.py
clado_observe/cdp/utils/screencast.py
clado_observe/cdp/utils/screenshot.py
clado_observe/cdp/utils/target_manager.py
clado_observe/utils/api_client.py
clado_observe/utils/vlm_evaluator.py
clado_observe-0.1.1.dist-info/METADATA
clado_observe-0.1.1.dist-info/WHEEL
clado_observe-0.1.1.dist-info/licenses/LICENSE.md
clado_observe-0.1.1.dist-info/RECORD
