Metadata-Version: 2.4
Name: clado-observe
Version: 0.1.1
Summary: Clado Observe
Project-URL: Homepage, https://github.com/clado-ai/observability
Project-URL: Issues, https://github.com/clado-ai/observability/issues
Author-email: Clado <david@clado.ai>
License: MIT
License-File: LICENSE.md
Keywords: clado,observe,sdk
Classifier: License :: OSI Approved :: MIT License
Classifier: Operating System :: OS Independent
Classifier: Programming Language :: Python :: 3
Requires-Python: >=3.11
Requires-Dist: aiohttp>=3.8.0
Requires-Dist: anthropic>=0.38.0
Requires-Dist: browser-use>=0.1.37
Requires-Dist: openai>=1.0.0
Requires-Dist: python-dotenv>=1.0.1
Requires-Dist: websockets>=12.0
